cogworks_data/__init__.py
cogworks_data/_utils.py
cogworks_data/audio.py
cogworks_data/language.py
cogworks_data/vision.py
cogworks_data-0.2.0.dist-info/LICENSE.txt
cogworks_data-0.2.0.dist-info/METADATA
cogworks_data-0.2.0.dist-info/WHEEL
cogworks_data-0.2.0.dist-info/top_level.txt
cogworks_data-0.2.0.dist-info/RECORD
