Metadata-Version: 2.1
Name: cogworks-data
Version: 0.2.0
Summary: Simple functions for downloading and accessing data for CogWorks.
Author: CogWorks Staff
Author-email: rsoklaski@gmail.com
License: MIT
Requires-Python: >=3.7
License-File: LICENSE.txt
Requires-Dist: pooch (>=1.6.0)
Requires-Dist: typing-extensions (>=4.1.0)
